kiwrious/__init__.py
kiwrious/sensor.py
kiwrious/sensordata.py
kiwrious/service.py
kiwrious/utility.py
kiwrious-0.0.7.dist-info/METADATA
kiwrious-0.0.7.dist-info/WHEEL
kiwrious-0.0.7.dist-info/licenses/LICENSE.txt
kiwrious-0.0.7.dist-info/RECORD
