Metadata-Version: 2.1
Name: kiwrious
Version: 0.0.7
Summary: Package for interacting with Kiwrious sensors
Author-email: David <dgil754@aucklanduni.ac.nz>
License-File: LICENSE.txt
Classifier: License :: OSI Approved :: MIT License
Classifier: Operating System :: OS Independent
Classifier: Programming Language :: Python :: 3
Requires-Python: >=3.7
Requires-Dist: pyserial
